aiornot/__init__.py
aiornot/async_client.py
aiornot/cli.py
aiornot/common_client.py
aiornot/exceptions.py
aiornot/req_builders.py
aiornot/settings.py
aiornot/sync_client.py
aiornot/types/__init__.py
aiornot/types/batch.py
aiornot/types/common.py
aiornot/types/enums.py
aiornot/types/image.py
aiornot/types/music.py
aiornot/types/text.py
aiornot/types/video.py
aiornot/types/voice.py
aiornot-0.1.0.dist-info/METADATA
aiornot-0.1.0.dist-info/WHEEL
aiornot-0.1.0.dist-info/entry_points.txt
aiornot-0.1.0.dist-info/licenses/LICENSE
aiornot-0.1.0.dist-info/RECORD
