Metadata-Version: 2.4
Name: aiornot
Version: 0.1.0
Summary: Python client for the AIORNOT API - detect AI-generated content in images, videos, audio, and text.
Project-URL: Homepage, https://aiornot.com/
Project-URL: Repository, https://github.com/aiornotinc/aiornot-python
Project-URL: Bug Tracker, https://github.com/aiornotinc/aiornot-python/issues
Project-URL: Documentation, https://github.com/aiornotinc/aiornot-python
Author-email: aiornot <support@aiornot.com>
License: MIT
License-File: LICENSE
Keywords: ai detection,aiornot,genai,generative ai
Classifier: Development Status :: 4 - Beta
Classifier: Intended Audience :: Developers
Classifier: License :: OSI Approved :: MIT License
Classifier: Operating System :: OS Independent
Classifier: Programming Language :: Python :: 3
Classifier: Programming Language :: Python :: 3.10
Classifier: Programming Language :: Python :: 3.11
Classifier: Programming Language :: Python :: 3.12
Classifier: Programming Language :: Python :: 3.13
Classifier: Topic :: Software Development :: Libraries :: Python Modules
Requires-Python: <3.14,>=3.10
Requires-Dist: aiofiles>=23.2.1
Requires-Dist: click>=8.1.7
Requires-Dist: httpx>=0.25.1
Requires-Dist: pydantic>=2.5.2
